qymeta/__init__.py
qymeta/qy/__init__.py
qymeta/qy/qy_nft.py
qymeta/qy_nft/__init__.py
qymeta/qy_nft/qy.py
qymeta/utils/__init__.py
qymeta/utils/sign.py
qymeta-0.0.4.dist-info/METADATA
qymeta-0.0.4.dist-info/WHEEL
qymeta-0.0.4.dist-info/top_level.txt
qymeta-0.0.4.dist-info/RECORD
