Metadata-Version: 2.1
Name: qymeta
Version: 0.0.4
Summary: QYmeta python SDK
Home-page: https://github.com/qymeta/qymeta_qy
Author: 草根之明
Author-email: 3907721@qq.com
Maintainer: 草根之明
Maintainer-email: 3907721@qq.com
License: MIT
Platform: all
Requires-Dist: requests
